Metadata-Version: 2.1
Name: Euro2020-API
Version: 0.0.1
Summary: Get insights from the Euro 2020 data.
Home-page: https://github.com/AnabeatrizMacedo241/NBA_analysis
Author: Ana Beatriz Macedo
Author-email: <anabeatrizmacedo241@gmail.com>
License: MIT
Keywords: API,football,euro,soccer,Sports
Platform: UNKNOWN
Classifier: Development Status :: 5 - Production/Stable
Classifier: Intended Audience :: Science/Research
Classifier: License :: OSI Approved :: MIT License
Classifier: Operating System :: OS Independent
Classifier: Programming Language :: Python :: 3.9
Classifier: Topic :: Database
Classifier: Topic :: Scientific/Engineering :: Information Analysis
